arango_rdf/__init__.py
arango_rdf/abc.py
arango_rdf/controller.py
arango_rdf/exception.py
arango_rdf/main.py
arango_rdf/typings.py
arango_rdf/utils.py
arango_rdf/meta/adb.trig
arango_rdf/meta/dc.trig
arango_rdf/meta/owl.trig
arango_rdf/meta/rdf.trig
arango_rdf/meta/rdfs.trig
arango_rdf/meta/xsd.trig
arango_rdf-2.0.0.dist-info/licenses/LICENSE
arango_rdf-2.0.0.dist-info/METADATA
arango_rdf-2.0.0.dist-info/WHEEL
arango_rdf-2.0.0.dist-info/top_level.txt
arango_rdf-2.0.0.dist-info/RECORD
