Metadata-Version: 2.4
Name: arango_rdf
Version: 2.0.0
Summary: Convert ArangoDB graphs to RDF & vice-versa.
Author-email: Anthony Mahanna <anthony.mahanna@arangodb.com>
License:                                  Apache License
Project-URL: Homepage, https://github.com/ArangoDB-Community/ArangoRDF
Keywords: arangodb,rdf,resource description framework,rdflib,adapter
Classifier: Intended Audience :: Developers
Classifier: License :: OSI Approved :: Apache Software License
Classifier: Operating System :: OS Independent
Classifier: Programming Language :: Python :: 3
Classifier: Programming Language :: Python :: 3.9
Classifier: Programming Language :: Python :: 3.10
Classifier: Programming Language :: Python :: 3.11
Classifier: Programming Language :: Python :: 3.12
Classifier: Programming Language :: Python :: 3.13
Classifier: Topic :: Utilities
Classifier: Typing :: Typed
Requires-Python: >=3.9
License-File: LICENSE
Requires-Dist: rdflib>=6.0.0
Requires-Dist: python-arango<9,>=8.1.7
Requires-Dist: cityhash>=0.4.6
Requires-Dist: requests>=2.27.1
Requires-Dist: rich>=12.5.1
Requires-Dist: setuptools>=45
Requires-Dist: isodate
Provides-Extra: dev
Requires-Dist: arango_datasets~=1.2; extra == "dev"
Requires-Dist: black==23.3.0; extra == "dev"
Requires-Dist: flake8==6.0.0; extra == "dev"
Requires-Dist: Flake8-pyproject; extra == "dev"
Requires-Dist: isort==5.12.0; extra == "dev"
Requires-Dist: mypy==1.4.1; extra == "dev"
Requires-Dist: pytest>=6.0.0; extra == "dev"
Requires-Dist: pytest-cov>=2.0.0; extra == "dev"
Requires-Dist: coveralls>=3.3.1; extra == "dev"
Requires-Dist: types-setuptools; extra == "dev"
Requires-Dist: sphinx; extra == "dev"
Requires-Dist: sphinx_rtd_theme; extra == "dev"
Dynamic: license-file
